Workbook

Sheet Comparison
A1: Kingdoms of Bharat vs. Age of Empires — Gameplay Element Comparison
A2: Baseline: Age of Empires II / IV core mechanics (per Age of Empires Fandom wiki 'Age' category). Compared against the Unity RTS project 'Kingdoms of Bharat' as documented in its own CLAUDE.md session log / roadmap. 'Assets Needed to Close Gap' lists concrete art/audio/UI assets required — code-only work is marked 'None'.
A4: Category | B4: AoE Gameplay Element | C4: What it does in AoE (II/IV reference) | D4: Status in Kingdoms of Bharat | E4: Project Evidence / Equivalent System | F4: Assets Needed to Close Gap | G4: Notes
A5: Core Progression | B5: Age / Age-up | C5: Players advance through fixed tiers (Dark->Feudal->Castle->Imperial in AoE II) unlocking units/buildings/techs. | D5: Implemented | E5: AgeProfile/UpgradeProgress hardcoded tier system; BuildMenu items are age-gated (e.g. Barracks placement gated by Age). | F5: None (code/data only). | G5: Deliberately hardcoded per CLAUDE.md, not CSV-migrated.
A6: Core Progression | B6: Technology / Tech tree | C6: Researchable upgrades at buildings, branching per civ. | D6: Implemented | E6: CSV-driven tech data (Assets/Design/Data/*.csv -> ScriptableObjects) read via DataRegistry; UniqueTechDefinition for civ-specific techs. | F6: Tech-tree UI icons per tech per civ if not already sourced (1 icon x ~5-15 techs x 5 civs) — not confirmed present or absent, flag to verify.
A7: Core Progression | B7: Civilization | C7: Distinct playable factions with unique units/bonuses/architecture. | D7: Implemented | E7: 5 civs: Chola, Vijayanagara, Rajput, Maurya, Maratha — each with unique buildings, units, bonuses, tech, and tinted soldier models. | F7: None further — civ roster is closed at 5 by design (Indian-kingdoms setting), not an AoE-style 30+ roster.
A8: Core Progression | B8: Civilization bonus | C8: Passive per-civ economic/military bonuses. | D8: Implemented | E8: Per-civ passive bonuses (CivPassiveBonusTests) e.g. Market spread, cavalry bonuses. | F8: None (code/data only).
A9: Core Progression | B9: Unique technology | C9: One tech per civ unlocking a powerful late-game effect. | D9: Implemented | E9: UniqueTechDefinition system, same bespoke-per-civ convention as TeamBonus. | F9: 1 tech-tree icon per civ if not already present — verify.
A10: Core Progression | B10: Score | C10: Numeric score tracked across military/economy/tech/society for ranking a match. | D10: Missing | E10: No scoring system found anywhere in the codebase or session log. | F10: UI: scoreboard panel art (frame + category icons: military/economy/technology/society, matching existing UIStyleTheme 9-slice style). | G10: Pure UI + code; no 3D/character assets needed.
A11: Core Progression | B11: Victory conditions | C11: Conquest, Score, Time Limit, Regicide, King of the Hill, etc. | D11: Partial | E11: Conquest (elimination-based, MatchManager.Evaluate) and Time Limit (GameSettings.TimeLimitMinutes: Off/15/30/45/60, population tiebreaker, Draw on a tie) both implemented and live-verified; mission-based objectives (MissionObjective/MissionTrigger) also exist for scripted campaign missions. Score-based, Regicide, and King of the Hill victory conditions remain unimplemented -- each depends on a system this sheet separately lists as Missing (Score itself; a King unit + special-death rule; a capturable map objective). | F11: None further for Conquest/Time Limit (code-only; the Victory/Defeat splash screen already existed via GameOverScreen.cs). Regicide needs 1 King unit model per civ (5); King of the Hill needs 1 Hill/Wonder marker prop -- only if those modes are pursued. | G11: Conquest/Time Limit closed 2026-09-03 (docs/PARTIAL_ELEMENTS_FIX_PLAN.md item 2). Score/Regicide/KotH intentionally deferred, not silently dropped.
A12: Core Progression | B12: Game modes | C12: Skirmish, Deathmatch, Regicide, Battle Royale, empire wars, etc. | D12: Missing | E12: Only scripted single missions found; no selectable game-mode system. | F12: UI: game-mode select screen art (mode icons/thumbnails, ~4-6 images) matching MissionSelectMenu's existing style. | G12: Mostly code/menu work; icon set is the only new asset need.
A13: Economy | B13: Resource (Wood/Food/Gold/Stone) | C13: Four core resources gathered and spent on units/buildings/tech. | D13: Implemented | E13: ResourceStockpile with Wood/Food/Gold/Stone, matches AoE II's 4-resource model. | F13: None — 4 resource icons already exist (wired into ResourceHUD).
A14: Economy | B14: Gather Point / Rally Point | C14: Set a flag so newly trained units or gathered resources auto-route to a location. | D14: Implemented | E14: RallyPoint system (bug-fixed for raycast/soft-lock issues). | F14: 1 rally-flag 3D prop/decal if not already present — verify visual exists, not just the logic.
A15: Economy | B15: Resource-specific drop-off buildings | C15: Lumber Camp / Mining Camp / Mill act as closer drop points for their resource. | D15: Implemented | E15: Lumber Camp, Mining Camp, Mill added (Phase 3.1); Gatherer.AcceptsDropOff restricts each to its resource, TownCenter stays universal. | F15: Per CLAUDE.md's own flagged gap: these 3 buildings currently use procedural-shape silhouettes, not sourced civ-specific art — needs 3 real building models x 5 civs (15 models) to match the rest of the building roster's visual bar. | G15: Explicitly flagged in CLAUDE.md as a real art-asset gap, not just a note here.
A16: Economy | B16: Villager Priority | C16: Idle-villager queue / auto-reassignment logic and UI hint. | D16: Missing | E16: No idle-worker/priority system found. | F16: 1 'idle villager' UI icon/button (small badge on ResourceHUD or a dedicated indicator) if implemented. | G16: Mostly code; one small icon asset.
A17: Economy | B17: Population cap | C17: Hard cap on total units, raised by Houses. | D17: Implemented | E17: Population tracked via ResourceStockpile; Houses present per civ. | F17: None.
A18: Economy | B18: Trade (caravans / trade routes) | C18: Trade Carts/Cogs move resources between Markets/allies for profit. | D18: Missing | E18: Market exists with a buy/sell price spread (economic trading of resources for gold) but no caravan/trade-route mechanic between players found. | F18: 1 Trade Cart unit model (land) + 1 Trade Cog/ship model (naval) x 5 civs (or 1 shared model if not civ-specific) = 2-10 models, plus a trade-route line VFX/decal. | G18: Biggest new-content item in Economy; needs real 3D asset sourcing, not just wiring.
A19: Economy | B19: Tribute | C19: Send resources directly to another player (with a tax). | D19: Missing | E19: No tribute mechanic found; DiplomacyRegistry covers alliance status only, not resource transfer. | F19: UI only: a small tribute panel/button set in the diplomacy screen. No 3D assets.
A20: Economy | B20: Renewable resource (Farms/Fish Traps) | C20: Farms auto-replant or degrade to 0 requiring reseed; Fish Traps are a placeable food building. | D20: Partial | E20: Farm now has real AoE II-style depletion (175-Food capacity) and a Wood-costed reseed (BeginReseed/StopReseed, 60 Wood full cost, using ConstructionSite.SpeedMultiplier's diminishing-returns curve for multi-worker reseeding); FarmWorker autonomously switches between harvesting and reseeding based on the Farm's own live depleted state, no new player order needed. Fish Trap still does not exist. | F20: None for Farm reseed (closed). Fish Trap: 1 model x 5 civs (5) -- still blocked on the user sourcing source models, per this project's 'asset sourcing is not Claude Code's job' rule. | G20: Farm half closed 2026-09-03 (docs/PARTIAL_ELEMENTS_FIX_PLAN.md item 5). Fish Trap explicitly deferred/asset-blocked, untouched.
A21: Economy | B21: Auto Scout | C21: Scout unit can be set to auto-explore the map. | D21: Missing | E21: No auto-explore behavior found. | F21: None — pure AI/pathing code.
A22: Buildings | B22: Building (general) | C22: Structures with HP, construction, and function (production, defense, economy). | D22: Implemented | E22: 9 building kinds per civ (TownCenter, Barracks, Tower, Market, Farm, House, Wall, Gate, Dock) — 45/45 civ-specific models complete. | F22: None for the base roster — fully sourced and wired.
A23: Buildings | B23: Architecture set (civ-distinct building style) | C23: Each civilization's buildings share one visual identity (material palette, silhouette language) distinct from other civs. | D23: Implemented (single-tier only — see 'Building Age-tier visual upgrade' below) | E23: Each civ's 9 buildings are separately modeled/sourced/skinned (Meshy AI pipeline), not palette-swapped — civs read as visually distinct. | F23: None for current single-tier art. See the dedicated 'Building Age-tier visual upgrade' row below for the real remaining asset gap this flags. | G23: User-flagged gap: AoE's architecture sets are not just civ-distinct, they also change per Age — that dimension is tracked separately below since it's a distinct, large asset requirement, not a rewording of this row.
A24: Buildings | B24: Building Age-tier visual upgrade | C24: In AoE, key buildings (Town Center, Walls, Towers, sometimes Barracks/Docks) visually change model/texture as the player advances Age — a Dark Age TC looks different from an Imperial Age TC of the same civ. | D24: MISSING — real, previously unflagged gap | E24: Every civ-specific building in this project (Roadmap Section 4/5 item 7) is a single static model per building type per civ, reused unchanged across all Age tiers; no per-Age variant exists for any of the 45 buildings. | F24: Full scope: (# age-sensitive buildings, typically TownCenter + Wall + Tower + Gate, i.e. 4) x (5 civs) x (age tiers beyond the first, e.g. 3 more if 4 total ages) = up to 60 additional building models/re-skins, each needing its own Meshy-pipeline import + rotation/scale pass like the existing 45. | G24: This is the specific gap the user asked to have flagged — a genuinely large new asset-sourcing task, not a code change.
A25: Buildings | B25: Wall / Tower defensive tier progression | C25: Palisade Wall -> Stone Wall (-> Fortified Wall); Watch Tower -> Guard Tower -> Keep — each tier is a separate upgrade with its own model and higher stats. | D25: MISSING | E25: This project's Wall and Tower are each a single fixed model per civ with no upgrade tiers; HP/armor upgrades (if any) would apply invisibly to the same mesh. | F25: 2-3 additional tiers x (Wall + Tower) x 5 civs = 20-30 additional building models, following the same import pipeline as the existing Wall/Tower assets. | G25: Related to, but distinct from, the Age-tier row above — this is a dedicated defensive-tech upgrade chain, not just an Age gate.
A26: Buildings | B26: Multi-builder construction | C26: Multiple workers speed up construction with diminishing returns. | D26: Implemented | E26: ConstructionSite.SpeedMultiplier: 1x/1.6x/1.9x/2.2x for 1-4 workers (AoE II-style diminishing curve). | F26: None (code/data only).
A27: Buildings | B27: Repairing | C27: Workers repair damaged buildings/ships/siege for a resource cost. | D27: Implemented | E27: Repairable/Repairer system, flat Wood-per-HP rate by unit class, wired to all 9 building kinds + Siege + naval units. | F27: Optional: repair hammer/sparks VFX if not already present — verify.
A28: Buildings | B28: Garrison | C28: Units can shelter inside buildings, some buildings gain attack power from garrisoned troops. | D28: Implemented | E28: GarrisonPoint (pooled capacity, any eligible land unit) generalized from the old single-slot Durg mechanic; TownCenter/Tower fire extra shots per garrisoned occupant. | F28: None (code/data only).
A29: Buildings | B29: Mobile building (packable siege, e.g. Trebuchet) | C29: Some siege units pack/unpack between mobile and stationary firing modes. | D29: Missing | E29: No pack/unpack mechanic found on Siege units. | F29: Siege unit needs a 2nd 'packed/wheeled' mesh state (or a rig with a fold/unfold animation) per civ that has a unique siege model — otherwise 1 shared packed model. | G29: Animation work (pack/unpack) in addition to modeling.
A30: Buildings | B30: Town Bell | C30: One-click command that garrisons all villagers into the nearest building for defense. | D30: Missing | E30: No Town-Bell-equivalent found. | F30: 1 UI button icon (matches BuildMenu command-card style) + optional bell-ring SFX/VFX on TownCenter.
A31: Buildings | B31: Damage-state visuals (rubble/smoke on low-HP buildings) | C31: Buildings visually crack, smoke, or show rubble as HP drops. | D31: Unclear / Needs Verification | E31: Not mentioned anywhere in the session log; HP is tracked (Attackable) but no visual-damage-state system confirmed. | F31: Damage-state textures/decals or a burning-VFX prefab per building tier if not already present — verify against the live scene before scoping further.
A32: Units & Combat | B32: Unit (general) | C32: Trainable military/economic actors with stats, movement, combat. | D32: Implemented | E32: Worker, Soldier, Archer, Cavalry, Spearman, Siege + unique units per civ. | F32: None for the base roster — models sourced and wired.
A33: Units & Combat | B33: Unit type / armor class | C33: Categorization (infantry/archer/cavalry/siege/naval/building) used for counters. | D33: Implemented | E33: UnitClass enum (Infantry/Archer/Cavalry/Siege/Naval/Building) drives CombatBonus/CounterMatrix. | F33: None (code/data only).
A34: Units & Combat | B34: Counter system | C34: Rock-paper-scissors bonuses (e.g. Archers beat Cavalry, Cavalry beats Infantry). | D34: Implemented | E34: CombatBonus.Multiplier + CounterMatrix (CSV, used for Spearman); Archer vs Cavalry tuned 1.5x->2.0x after a numeric audit. | F34: None (code/data only).
A35: Units & Combat | B35: Armor (melee/pierce split) | C35: Two separate armor stats reducing melee vs. ranged damage independently. | D35: Unclear / Needs Verification | E35: ClassArmorBonus/ClassDamageBonus exist per unit class, but no evidence of a distinct melee-armor vs pierce-armor split like AoE II's. | F35: None (code/data only) — this is a formula-design question, not an asset gap.
A36: Units & Combat | B36: Area of Effect / Trample damage | C36: Siege deals splash damage to units near the target; cavalry tramples infantry it charges through. | D36: Implemented | E36: Siege splash/area damage (HostileFilter, MeleeAttacker.SetSplashRadius) and Cavalry trample (SetSplashRadius gained an optional damageMultiplier param; CavalryFactory wires a 1.25 radius at 35% secondary damage) both implemented and live-verified through the real CavalryFactory/SoldierFactory/MeleeAttacker.Tick production path. | F36: None (code only). The existing per-hit particle burst already reads correctly for trample hits -- no new VFX needed. | G36: Cavalry trample closed 2026-09-03 (docs/PARTIAL_ELEMENTS_FIX_PLAN.md item 3).
A37: Units & Combat | B37: Unit formation | C37: Groups move/fight in Line, Staggered, Box, etc. formations. | D37: Implemented | E37: GroupFormation with Line and Staggered layouts (Staggered depth-offset fixed to actually reduce splash casualties). | F37: Optional: formation-select UI icons (Line/Staggered/Box) if a player-facing formation picker doesn't already exist — verify.
A38: Units & Combat | B38: Unit stance | C38: Aggressive / Defensive / Stand Ground / No Attack behavior toggle per unit. | D38: Missing | E38: No stance system found; worker combat response (Fight/Flee) is a fixed per-civ default (WorkerCombatResponseDefaults), not a player-toggleable stance. | F38: 4 stance UI icons (matching SelectedUnitPanel's existing icon style). | G38: Mostly code; small icon set.
A39: Units & Combat | B39: Worker self-defense | C39: Villagers auto-fight back (or flee) when attacked while gathering. | D39: Implemented | E39: Attackable.OnDamaged + CombatResponse(Fight/Flee) + WorkerCombatResponseDefaults; all civs fight back except Maratha (flees, by design). | F39: None (code/data only).
A40: Units & Combat | B40: Healing (unit HP recovery) | C40: Units heal over time near friendly buildings, or via a Monk/healer unit. | D40: Missing | E40: Repair exists for buildings/siege/ships; no passive or active HP regeneration/healing found for living units. | F40: If adding a dedicated healer unit: 1 model x 5 civs (5) + heal-beam/aura VFX + SFX. Passive near-TownCenter healing needs no new asset, only a heal-tick + a small green-cross-style VFX pulse.
A41: Units & Combat | B41: Regeneration | C41: Passive slow HP recovery outside combat. | D41: Missing | E41: Not found. | F41: None — code only (optionally a subtle HP-bar pulse VFX).
A42: Units & Combat | B42: Conversion (Monk-style) | C42: A unit (e.g. Monk) can convert enemy units/buildings to your side. | D42: Missing | E42: No conversion mechanic or religious/hero unit type found. | F42: 1 new religious/hero unit model x 5 civs (5, since the setting has strong Indian religious-figure options — e.g. temple priest/guru) + conversion beam VFX + chant SFX + a Temple/Monastery building x 5 civs if not reusing an existing structure. | G42: Largest single new-content item in Combat — a full new unit class plus a possible new building type.
A43: Units & Combat | B43: Attack ground | C43: Manually target a ground point instead of a unit (for siege/AoE weapons). | D43: Missing | E43: Not found. | F43: 1 ground-target cursor/reticle icon (matches HoverTooltip's existing cursor-state set). | G43: Mostly code; one icon asset.
A44: Units & Combat | B44: Elevation bonus | C44: Units on higher terrain get an attack bonus / defenders on a hill are harder to hit. | D44: Missing | E44: No terrain-height combat interaction found. | F44: None — pure code (terrain height sampling + damage-multiplier), no new assets.
A45: Units & Combat | B45: Snare | C45: Special ability that roots/immobilizes a target unit. | D45: Missing | E45: Not found (no ability system at all — see 'Ability' row). | F45: 1 root/entangle VFX + SFX, plus a status-icon on the target's unit panel.
A46: Units & Combat | B46: Stealth mode | C46: Certain units can go invisible/hidden outside of LOS or in forest. | D46: Missing | E46: Not found. | F46: A transparency/dissolve shader (likely already achievable with URP without new art) + a 'detected' status icon. | G46: Mostly a shader/material tweak, minimal new art.
A47: Units & Combat | B47: Land mine | C47: Buried explosive unit that detonates on enemy contact. | D47: Missing | E47: Not found. | F47: 1 mine prop model (or reuse a simple crate/rock decal) x possibly per civ, + explosion VFX + SFX.
A48: Units & Combat | B48: Pass-through damage | C48: A projectile continues past its first target and can hit units behind it. | D48: Missing | E48: Not found. | F48: None — pure code (raycast-through logic), reuses existing projectile VFX.
A49: Units & Combat | B49: Ability (active unit abilities) | C49: Special active abilities on hero/special units (III/IV-style). | D49: Missing | E49: No active-ability system found; only passive team/civ bonuses and auras-by-proxy. | F49: Depends entirely on which abilities are designed — each needs its own icon + VFX + SFX; scope this only once specific abilities are chosen.
A50: Units & Combat | B50: Aura | C50: Passive buffs radiating from a unit/building to nearby friendlies. | D50: Missing | E50: No spatial aura system; team bonuses are alliance-wide flat modifiers, not proximity-based. | F50: 1 ground-decal 'aura ring' VFX (shared, reusable across any unit/building that gets one) + a buff-icon on affected units' panels.
A51: Units & Combat | B51: Rate of Fire | C51: Per-unit attack interval/cooldown between shots. | D51: Implemented | E51: Explicit per-unit attack intervals (e.g. BoatAttacker 1.5s vs MeleeAttacker 1.0s), documented as a deliberate design choice. | F51: None.
A52: Units & Combat | B52: Range | C52: Melee vs ranged attack distance. | D52: Implemented | E52: Archer/ranged units and siege have distinct ranges (implied throughout combat systems; splash radius separately tuned). | F52: None.
A53: Units & Combat | B53: Speed | C53: Unit movement speed, upgradeable per civ/unit. | D53: Implemented | E53: Move-speed stats exist; e.g. Maratha team bonus is +10% Cavalry move speed. | F53: None.
A54: Units & Combat | B54: Hit points | C54: Core HP stat all units/buildings share. | D54: Implemented | E54: Attackable.TakeDamage / HP system underlies all combat. | F54: None.
A55: Units & Combat | B55: Spawning | C55: Units produced from a building's queue appear at/near it. | D55: Implemented | E55: Unit factories (SoldierFactory, SiegeFactory, WarGalleyFactory, etc.). | F55: None.
A56: Units & Combat | B56: Taunt | C56: Cosmetic voice-line command with no gameplay effect. | D56: Missing | E56: Not found. | F56: Voice-line audio recordings/clips per civ (or per unit) — a content/VO sourcing task, not code.
A57: Units & Combat | B57: Per-civ gear/prop variants (helmet/shield/weapon style) | C57: Soldiers of different civs carry visually distinct weapons/armor, not just a palette tint. | D57: Missing (already scoped in project's own roadmap) | E57: CLAUDE.md documents this as a known, already-specced gap — the shared Human Character Dummy body is tinted per civ but all civs currently use the exact same generic weapon per unit type (Assets/Resources/Weapons/ has one generic weapon per type, no civ variants). | F57: Per the project's own spec: helmet + shield + weapon model set x 5 civs x however many unit types get unique gear — a real, sizeable asset-sourcing task already flagged internally, included here for completeness. | G57: Restated from CLAUDE.md's own roadmap rather than newly discovered.
A58: Units & Combat | B58: Crusader Knight body-swap (base soldier model replacement) | C58: N/A — internal project item, included since it's a live, currently-blocked asset gap. | D58: Blocked on asset re-sourcing | E58: 2 source glTF files (TemplarKnight/HospitalierKnight) were deleted in a 'confirmed-unused asset scrap' commit and are not recoverable from git history; the ~247x humanScale rig anomaly and weapon re-parenting work can't resume until replacements exist. | F58: 2 new humanoid biped models (FBX or glTF), modeled in meters near ~1.9-unit worker height, standard Humanoid rig, no embedded animation, weapons separable/re-parentable to a hand bone (see this file's own sourcing spec). | G58: Carried over from the project's own roadmap so the asset need is visible in one place.
A59: Naval | B59: Naval units / Docks | C59: Ships built from a Dock, gather Fish, transport, and fight (incl. War Galleys). | D59: Implemented | E59: Dock building, War Galley unit, BoatAttacker; naval balance pass applied ClassArmorBonus/ClassDamageBonus(Naval) to match land factories. | F59: None for current roster (War Galley + Dock, all 5 civs).
A60: Naval | B60: Naval unit variety (Fishing Boat, Transport, Fire Ship, Cannon Galleon tiers) | C60: AoE navies have several distinct ship roles/tiers, not just one warship. | D60: Missing | E60: Only War Galley (combat) is documented; no Fishing Boat, Transport Ship, or upgraded-tier warship found. | F60: 1 Fishing Boat + 1 Transport Ship model (shared or per-civ) = 2-10 models, plus any additional War Galley upgrade-tier models if tiered naval combat is wanted.
A61: Multiplayer & Tech | B61: Multiplayer (LAN/online) | C61: Real-time synchronized play between human players. | D61: Implemented (LAN only) | E61: Deterministic lockstep LAN transport MVP: NetworkId, LanTransport (raw TCP), NetworkDriver, NetworkMatch, StateHash exchange, host-authoritative desync detection/resync — live-verified over real TCP sockets. Online matchmaking/NAT traversal explicitly deferred to end of project; true cross-machine determinism testing still needs a second physical machine. | F61: None — this is transport/netcode, no art assets.
A62: Multiplayer & Tech | B62: Diplomacy | C62: Ally/neutral/enemy relations, tribute, shared vision. | D62: Partial | E62: DiplomacyRegistry alliance status confirmed already wired to a real player-facing stance UI (DiplomacyMenu.cs, F11, War/Allied toggle per faction) -- this was 'unconfirmed,' not actually missing. Tribute now implemented (Tribute.Send, 20% tax, not gated by alliance status per AoE II's own rule) with 4 flat-amount tribute buttons per faction row in DiplomacyMenu. Shared vision between allies remains unimplemented -- explicitly deferred, since it depends on the Fog of War / Line of Sight system this sheet separately lists as Missing. | F62: None for stance UI/tribute (closed, reused existing civ crest icons). Shared vision needs no new assets itself but is blocked on Fog of War's own shader/rendering work existing first. | G62: Stance UI confirmed + Tribute closed 2026-09-03 (docs/PARTIAL_ELEMENTS_FIX_PLAN.md item 4). Shared vision intentionally out of scope, not silently dropped.
A63: Multiplayer & Tech | B63: Signal Allies / Flare | C63: Ping the minimap to alert allies. | D63: Missing | E63: No minimap found at all (see UI section), so no flare mechanic either. | F63: 1 flare/ping VFX (ground ring pulse) + minimap ping icon — blocked on Minimap existing first.
A64: Multiplayer & Tech | B64: Artificial intelligence | C64: Computer-controlled opponent that builds, expands, and fights. | D64: Unclear / Needs Verification | E64: An 'aiCivilization' default faction exists in CivilizationSetup (used in the dedup-guard bugfix), implying an AI-controlled faction, but no AI behavior/build-order system is documented — depth unverified. | F64: None — pure code/behavior-tree work, no art assets.
A65: Multiplayer & Tech | B65: Cheat codes | C65: Debug/fun commands typed in chat. | D65: Missing | E65: Not found. | F65: None.
A66: UI / UX | B66: User interface (HUD, menus) | C66: Resource HUD, unit panels, build menu, tooltips, settings. | D66: Implemented | E66: ResourceHUD, SelectedUnitPanel (with HP bar), BuildMenu (command-card icons), HoverTooltip, CivPicker, MissionSelectMenu, Settings modal — full art pass done and pixel-verified. | F66: None for what's built.
A67: UI / UX | B67: Hotkey | C67: Keyboard shortcuts for building/training/commands. | D67: Implemented | E67: Full hotkey coverage across BuildMenu (Barracks/TownCenter/Dock training and research, Ungarrison, all building placements) centralized into BuildMenu.Update(), fixing a real pre-existing bug along the way (a hotkey previously fired at every idle building of that type instead of just the selected one). Every binding registered in SettingsMenu.Actions; an optional F1 hotkey-reference overlay panel was added (HotkeyOverlay.cs). Market buy/sell intentionally stayed click-only, matching AoE convention. | F67: None (code only) -- the F1 overlay reuses UIStyleTheme's existing 9-slice style, no new art. | G67: Closed 2026-09-03 (docs/PARTIAL_ELEMENTS_FIX_PLAN.md item 1).
A68: UI / UX | B68: Cursor states | C68: Distinct cursor icon per context (move/attack/gather/build/invalid). | D68: Implemented | E68: 5 cursor states wired via HoverTooltip.ResolveCursorState, using closest-available substitute art where the ideal asset wasn't sourced. | F68: Project's own documented gap: the 5 wired cursors are generic Asset-Store substitutes, not the UI art brief's purpose-made spec — 5 custom 32x32 cursor icons to fully close this.
A69: UI / UX | B69: Player / Team color coding | C69: Every unit and building carries a small color-coded accent (tunic, shield, roof cloth/trim) matching its owning player's assigned slot color, independent of civilization skin — lets players instantly tell friend from foe/ally from enemy on the battlefield and minimap, and UI panels/icons pick up the same color. | D69: Missing | E69: User-confirmed 2026-09: the project currently tints per-CIVILIZATION (e.g. Soldier models tinted per civ), not per-PLAYER-SLOT — two humans on the same civ, or the same civ used by different players across matches, would have no way to visually distinguish them. No accent-only color system (small painted sections vs. AoE II's subtle-highlight convention) was found; also has no minimap to show colored blips on (Mini map is separately Missing above). | F69: A tintable color-mask channel/material setup on every unit and building (shared shader parameter driven by player slot, not a new model) — technically a material/shader task across the existing 45 buildings + full unit roster, not new 3D assets. UI selection-panel/icon accent recoloring is a small UI-only addition. | G69: Distinct from civ-specific skinning, which already exists — this is the orthogonal player-identity layer AoE always keeps on top of it. Blocked in part on Mini map existing before the minimap-blip half can be finished, but the on-unit/on-building accent half can be built independently now.
A70: UI / UX | B70: Mini map | C70: Small overview map showing units/terrain/fog, click-to-navigate. | D70: Missing | E70: No minimap system found anywhere in the codebase or session log — a real, notable gap versus AoE. | F70: Minimap frame art (matches UIStyleTheme 9-slice style) + per-unit-type minimap blip icons (~1 icon per unit class, reusable across civs via tint) + terrain minimap render pipeline (code, not art). | G70: Frame + blip icons are the concrete new-art need; the map-rendering itself is code.
A71: UI / UX | B71: Fog of War / Line of Sight | C71: Unexplored/unseen areas hidden or greyed out; vision radius per unit. | D71: Missing | E71: No fog-of-war or per-unit vision-radius system found. | F71: A fog/shroud shader + explored-vs-visible grey-out texture treatment (art-adjacent shader work, not a modeled asset) + per-unit sight-radius data (code/data). | G71: Primarily a shader + rendering-pipeline task, not traditional 3D/2D asset sourcing.
A72: UI / UX | B72: Scenario Editor | C72: In-game tool to build custom maps/missions/triggers. | D72: Implemented | E72: A real in-game, player-facing Scenario Editor now exists (ScenarioEditorMenu.cs, opened via MissionSelectMenu's 'Create Scenario' button): a faction-scoped placement palette (click-place/drag-move/right-click-delete), an Objectives/Triggers authoring tab with per-kind bespoke input widgets (cycle-button fields for Faction/Resource/building-type params instead of free text), Save/Load/Play, a saved-scenario browse list on MissionSelectMenu, richer command-card palette icons, and multiplayer LAN play of a custom scenario (real HostHello scenario exchange, real Enemy-AiController gating). A separate RectMask2D over-culling rendering bug in the Objectives tab (past ~7 rows) was found during widget testing and has since been fixed (a wrong anchor point on a growing scroll-content rect, not an engine bug). | F72: None (code only) -- reuses existing command-card icon assets and UIStyleTheme's 9-slice panels. | G72: Light path + heavy-path sessions 1-6 all closed 2026-09-03 (docs/PARTIAL_ELEMENTS_FIX_PLAN.md item 6); RectMask2D follow-up fixed the same day.
A73: Content & Meta | B73: Soundtrack / Music | C73: Background music per age/civ/context. | D73: Not yet implemented (scoped) | E73: Scoped: self-serve CC0 tracks from Kenney.nl, same sourcing approach as the existing SFX pass (SfxPlayer.cs). No blocker, not started. | F73: CC0 music tracks from Kenney.nl (audio files only, no code assets) — count depends on how many context buckets (menu/civ-pick/in-game per age/victory/defeat) are wanted.
A74: Content & Meta | B74: Sound effects | C74: Combat/UI/ambient SFX. | D74: Implemented | E74: SfxPlayer.cs already wired and used as the precedent for the Music sourcing plan. | F74: None for what's wired; any new mechanic added above (Conversion, Snare, Trade, etc.) will need its own SFX per the asset list on that row.
A75: Content & Meta | B75: Tutorial | C75: Guided first-time-player mission teaching core mechanics. | D75: Not yet implemented (scoped) | E75: Scoped: rides the existing mission-objective system (MissionObjective/MissionTrigger/MissionSelectMenu), pure content authoring, no new system needed. Not started. | F75: None (content/data authoring only, no new art).
A76: Content & Meta | B76: Performance profiling | C76: Frame-time/memory profiling to catch bottlenecks in large matches. | D76: Not yet implemented (scoped) | E76: Scoped: tool is ready (mcp__UnityMCP__manage_profiler), just needs a run against a realistic large-match scenario. Not started. | F76: None — pure engineering task.
A77: Content & Meta | B77: Store / marketing assets | C77: Screenshots, trailer, store page copy for release. | D77: Blocked on user decision | E77: Scoped: the one genuinely blocked 'everything else' item — needs an explicit user decision on whether public release is even a goal before scoping further. | F77: Store capsule/header images, trailer video, 4-8 marketing screenshots, store description copy — full scope pending the release-intent decision.
A78: Content & Meta | B78: README / documentation accuracy | C78: Docs describing current game scope for new contributors/players. | D78: Confirmed stale (scoped fix ready) | E78: README confirmed badly stale — still describes the original single-map/3-civ/no-naval prototype and stops its milestone list at 26, missing 5-civ art, naval, LAN multiplayer, diplomacy, and the full worker-mechanics audit. Fix scoped, zero blocker, not started. | F78: None — pure documentation writing.
A79: Content & Meta | B79: Dialogue lines | C79: Voiced/text lines for units and mission narrative. | D79: Unclear / Needs Verification | E79: Not addressed anywhere in the session log; likely absent but not explicitly audited. | F79: Voice-over recordings per unit-select/move/attack line, per civ (or shared) — a VO sourcing/recording task if wanted; text-only dialogue needs only writing.

Sheet Summary
A1: Summary — Status Counts
A3: Status | B3: Count | C3: % of Elements
A4: Implemented | B4: =COUNTIF(Comparison!D:D,A4) | C4: =B4/75
A5: Missing | B5: =COUNTIF(Comparison!D:D,A5) | C5: =B5/75
A6: Partial | B6: =COUNTIF(Comparison!D:D,A6) | C6: =B6/75
A7: Implemented (single-tier only — see 'Building Age-tier visual upgrade' below) | B7: =COUNTIF(Comparison!D:D,A7) | C7: =B7/75
A8: MISSING — real, previously unflagged gap | B8: =COUNTIF(Comparison!D:D,A8) | C8: =B8/75
A9: MISSING | B9: =COUNTIF(Comparison!D:D,A9) | C9: =B9/75
A10: Unclear / Needs Verification | B10: =COUNTIF(Comparison!D:D,A10) | C10: =B10/75
A11: Missing (already scoped in project's own roadmap) | B11: =COUNTIF(Comparison!D:D,A11) | C11: =B11/75
A12: Blocked on asset re-sourcing | B12: =COUNTIF(Comparison!D:D,A12) | C12: =B12/75
A13: Implemented (LAN only) | B13: =COUNTIF(Comparison!D:D,A13) | C13: =B13/75
A14: Not yet implemented (scoped) | B14: =COUNTIF(Comparison!D:D,A14) | C14: =B14/75
A15: Blocked on user decision | B15: =COUNTIF(Comparison!D:D,A15) | C15: =B15/75
A16: Confirmed stale (scoped fix ready) | B16: =COUNTIF(Comparison!D:D,A16) | C16: =B16/75
A17: Total elements assessed | B17: =SUM(B4:B16) | C17: =SUM(C4:C16)
A20: Read this sheet alongside the 'Comparison' tab for per-element detail, evidence, and required assets.
A22: By Category
A23: Category | B23: Implemented | C23: Total
A24: Core Progression | B24: =COUNTIFS(Comparison!A:A,A24,Comparison!D:D,"Implemented")+COUNTIFS(Comparison!A:A,A24,Comparison!D:D,"Implemented (LAN only)") | C24: =COUNTIF(Comparison!A:A,A24)
A25: Economy | B25: =COUNTIFS(Comparison!A:A,A25,Comparison!D:D,"Implemented")+COUNTIFS(Comparison!A:A,A25,Comparison!D:D,"Implemented (LAN only)") | C25: =COUNTIF(Comparison!A:A,A25)
A26: Buildings | B26: =COUNTIFS(Comparison!A:A,A26,Comparison!D:D,"Implemented")+COUNTIFS(Comparison!A:A,A26,Comparison!D:D,"Implemented (LAN only)") | C26: =COUNTIF(Comparison!A:A,A26)
A27: Units & Combat | B27: =COUNTIFS(Comparison!A:A,A27,Comparison!D:D,"Implemented")+COUNTIFS(Comparison!A:A,A27,Comparison!D:D,"Implemented (LAN only)") | C27: =COUNTIF(Comparison!A:A,A27)
A28: Naval | B28: =COUNTIFS(Comparison!A:A,A28,Comparison!D:D,"Implemented")+COUNTIFS(Comparison!A:A,A28,Comparison!D:D,"Implemented (LAN only)") | C28: =COUNTIF(Comparison!A:A,A28)
A29: Multiplayer & Tech | B29: =COUNTIFS(Comparison!A:A,A29,Comparison!D:D,"Implemented")+COUNTIFS(Comparison!A:A,A29,Comparison!D:D,"Implemented (LAN only)") | C29: =COUNTIF(Comparison!A:A,A29)
A30: UI / UX | B30: =COUNTIFS(Comparison!A:A,A30,Comparison!D:D,"Implemented")+COUNTIFS(Comparison!A:A,A30,Comparison!D:D,"Implemented (LAN only)") | C30: =COUNTIF(Comparison!A:A,A30)
A31: Content & Meta | B31: =COUNTIFS(Comparison!A:A,A31,Comparison!D:D,"Implemented")+COUNTIFS(Comparison!A:A,A31,Comparison!D:D,"Implemented (LAN only)") | C31: =COUNTIF(Comparison!A:A,A31)
A34: Rows with a concrete new asset requirement (excluding 'None')
A35: =COUNTIF(Comparison!F:F,"None*")
A36: rows say 'None' (code-only); the rest of the table's rows list real assets to source.

Sheet Units
A1: Unit Roster & Attributes — Age of Empires IV vs. Kingdoms of Bharat
A2: Baseline: Age of Empires IV's generic unit roster (Economic / Land Military / Religious / Naval Military), its unique-unit convention, and its core per-unit attribute model (cost, training time, LOS, HP, speed, armor, attacks, abilities, auras). Compared against Kingdoms of Bharat's actual unit roster as documented in CLAUDE.md.
A4: Category | B4: AoE IV Unit / Attribute | C4: Role / Description (AoE IV reference) | D4: Status in Kingdoms of Bharat | E4: Project Evidence / Equivalent System | F4: Assets Needed to Close Gap | G4: Notes
A5: Economic Unit | B5: Villager | C5: Gathers resources, constructs and repairs buildings. | D5: Partial — functional systems complete, visuals not sourced | E5: User-confirmed 2026-09: the Worker unit's gameplay is complete (gathers Wood/Food/Gold/Stone, builds via Builder/ConstructionSite, repairs via Repairer), but its visual model is still the bare generic humanoid dummy with no clothing, gear, or civ-specific skin — unlike the 45 fully-sourced civ buildings and the tinted (if generic-weaponed) Soldier models. | F5: 1 Villager model/texture per civ (5), following the same Meshy-pipeline sourcing process already used for the 45 civ buildings — clothing/skin appropriate to each of the 5 kingdoms, at minimum a civ-tint pass matching the Soldier convention. | G5: Flagged directly by the user during a live playtest — this is a confirmed, visible gap, not an inference from the session log.
A6: Economic Unit | B6: Trader (land) | C6: Moves between Trade Posts / allied Markets to generate gold. | D6: Missing | E6: Market exists with a buy/sell price spread (Chola's civ bonus tunes it), but no mobile Trader unit or Trade Post network — trading today is a passive sell action, not a unit-driven route. | F6: 1 Trader unit model x 5 civs (or 1 shared model) if implemented. | G6: Depends on the Trade element already flagged Missing in the main Comparison tab.
A7: Economic Unit | B7: Fishing Boat | C7: Collects Fish from water tiles. | D7: Missing | E7: No fishing/naval-gather unit found; Dock only produces the combat War Galley. | F7: 1 Fishing Boat model (shared or per-civ). | G7: Also listed under Naval unit variety in the main Comparison tab.
A8: Economic Unit | B8: Transport Ship | C8: Ferries land units across water. | D8: Missing | E8: Not found. | F8: 1 Transport Ship model (shared or per-civ).
A9: Economic Unit | B9: Trade Ship | C9: Naval counterpart to Trader — trades with Trade Posts/allied Docks. | D9: Missing | E9: Not found; depends on both the Trade element and a Fishing/Transport-style naval economy unit existing first. | F9: 1 Trade Ship model (shared or per-civ).
A10: Land Military Unit | B10: Spearman | C10: Light anti-cavalry melee infantry. | D10: Implemented | E10: Spearman unit exists; CounterMatrix (CSV) drives its cavalry-counter bonus specifically (the one unit type that uses CounterMatrix rather than CombatBonus). | F10: None.
A11: Land Military Unit | B11: Man-at-Arms (general heavy melee infantry) | C11: General-purpose heavy melee infantry, upgrade path from basic infantry. | D11: Implemented (as generic 'Soldier') | E11: Project's Soldier unit fills this generic-melee-infantry role; no separate light/heavy melee tiering, one generic type. | F11: None. | G11: Naming differs (Soldier vs Man-at-Arms) but the functional role matches.
A12: Land Military Unit | B12: Archer | C12: Low-attack ranged infantry, anti-light-infantry. | D12: Implemented | E12: Archer unit exists; Archer-vs-Cavalry bonus explicitly tuned (1.5x -> 2.0x) after a numeric audit. | F12: None.
A13: Land Military Unit | B13: Crossbowman (anti-heavy ranged) | C13: Upgrade/variant ranged infantry effective against heavy units. | D13: Missing | E13: Only one generic Archer tier exists; no distinct anti-heavy ranged unit. | F13: None (stat variant of existing Archer — no new model required if reusing Archer's art with a recolor/tag).
A14: Land Military Unit | B14: Handcannoneer (gunpowder ranged infantry) | C14: High-attack general-purpose ranged infantry from the gunpowder era. | D14: Missing — design question | E14: Not found. Whether this belongs in the roster at all depends on the project's target historical period for each civ (gunpowder-era units may be anachronistic for some of the 5 kingdoms/ages covered) — flag to the user rather than assume. | F14: 1 unit model x civs where historically appropriate. | G14: Needs a scope decision before sizing further.
A15: Land Military Unit | B15: Scout (non-upgradable early-game scout) | C15: Cheap, fast early unit dedicated to map exploration. | D15: Missing | E15: No dedicated scout unit found; Auto Scout (main Comparison tab) is also Missing, consistent with no scout role existing at all. | F15: 1 unit model x 5 civs (or 1 shared model).
A16: Land Military Unit | B16: Horseman (light anti-ranged cavalry) | C16: Light melee cavalry, strong vs. ranged units. | D16: Implemented (as generic 'Cavalry') | E16: Project's Cavalry unit fills this role; team bonus data confirms it has real move-speed/damage stats (Maratha +10% move speed, Rajput +1 flat damage). | F16: None.
A17: Land Military Unit | B17: Knight / Lancer (heavy general cavalry) | C17: Heavier melee cavalry, general-purpose shock unit. | D17: Partial | E17: Same generic Cavalry unit covers this role too — no separate light-vs-heavy cavalry tiering exists, one unit does both jobs. | F17: None for a stat-variant approach; a new model only if a visually distinct heavy-cavalry tier is wanted.
A18: Land Military Unit | B18: Battering Ram (anti-building, can garrison infantry, no splash) | C18: Early, cheap, short-range siege focused purely on breaking buildings; infantry can garrison inside for protection. | D18: Missing | E18: Project's one generic Siege unit deals splash/area damage (Mangonel-like), not the no-splash pure-anti-building Ram role; no garrison-carrying siege found (GarrisonSeeker was explicitly NOT added to Siege units, per this project's own design decision). | F18: 1 unit model x 5 civs if a distinct Ram tier is added. | G18: Excluding Siege from garrisoning was a deliberate decision already documented — a Ram would need to deliberately break that rule for itself only.
A19: Land Military Unit | B19: Siege Tower (wall-scaling transport) | C19: Carries infantry to the top of Stone Walls. | D19: Missing | E19: No wall-scaling mechanic or unit found; ties to the Wall/Tower tier system also flagged Missing in the main Comparison tab. | F19: 1 unit model x 5 civs.
A20: Land Military Unit | B20: Mangonel (area-damage siege) | C20: Ranged siege dealing area-of-effect damage, strong vs. massed ranged units. | D20: Implemented (as the project's one generic 'Siege' unit) | E20: The project's Siege unit's splash/area damage (HostileFilter, MeleeAttacker.SetSplashRadius, live-verified vs. formations) matches the Mangonel's role directly. | F20: None. | G20: This is the one AoE siege role the project's generic Siege unit actually matches; the other 4 siege roles below are not separately represented.
A21: Land Military Unit | B21: Counterweight Trebuchet (long-range anti-building) | C21: Very long range, high anti-building damage, no splash. | D21: Missing | E21: Only the one generic (Mangonel-like) Siege type exists — no long-range pure-anti-building tier. | F21: 1 unit model x 5 civs if a distinct Trebuchet tier is added.
A22: Land Military Unit | B22: Springald (anti-infantry, pass-through damage) | C22: Precise anti-infantry siege whose bolt passes through and can hit units behind the target. | D22: Missing | E22: Not found; Pass-through damage itself is already flagged Missing in the main Comparison tab (pure code gap, no new asset needed for the mechanic itself). | F22: 1 unit model x 5 civs if a distinct Springald tier is added.
A23: Land Military Unit | B23: Bombard (gunpowder anti-building) | C23: Powerful late-game gunpowder siege, high anti-building damage. | D23: Missing — same design question as Handcannoneer | E23: Not found; gunpowder-era appropriateness depends on each civ's target historical period. | F23: 1 unit model x civs where historically appropriate.
A24: Religious Unit | B24: Monk / Imam / Shaman (religious unit) | C24: Converts enemy units/buildings, heals friendly units, carries relics. | D24: Missing | E24: No religious/healer unit type found — matches the Conversion and Healing gaps already flagged Missing in the main Comparison tab's Combat section. | F24: 1 religious-figure unit model x 5 civs (e.g. temple priest/guru per kingdom) + a Temple/Monastery building if not reusing an existing structure. | G24: Single biggest new-unit content item — ties together 3 separate Missing mechanics (Conversion, Healing, Relic) into one unit type.
A25: Naval Military Unit | B25: Archer ship | C25: Fast ranged naval unit, generic across most civs. | D25: Missing | E25: Not found as a distinct type — see Warship row below for the one naval combat unit that does exist. | F25: 1 ship model (shared or per-civ).
A26: Naval Military Unit | B26: Springald ship | C26: Naval siege ship, anti-ship precision damage. | D26: Missing | E26: Not found. | F26: 1 ship model (shared or per-civ).
A27: Naval Military Unit | B27: Incendiary ship (Fire Ship) | C27: Naval unit that sets enemy ships ablaze at close range. | D27: Missing | E27: Not found; also listed under Naval unit variety in the main Comparison tab. | F27: 1 ship model (shared or per-civ) + fire/burn VFX.
A28: Naval Military Unit | B28: Warship (generic heavy naval combat ship) | C28: Core naval combat vessel. | D28: Implemented (as the project's one generic 'War Galley') | E28: War Galley + BoatAttacker exist and were explicitly balanced (ClassArmorBonus/ClassDamageBonus(Naval) applied to match land factories' convention). | F28: None. | G28: This is the only one of the 4 generic naval combat types the project actually has — the other 3 are undifferentiated from it.
A29: Naval Military Unit | B29: Culverin (semi-unique Bombard variant, faster fire rate) | C29: Lower-damage, faster-firing gunpowder siege ship/unit, available to a few civs only. | D29: Missing | E29: Not found; depends on the Bombard gap above existing first. | F29: 1 unit/ship model if implemented.
A30: Naval Military Unit | B30: Ribauldequin (semi-unique anti-mass-melee gunpowder siege) | C30: Powerful gunpowder siege strong specifically against massed melee units, available to a few civs only. | D30: Missing | E30: Not found. | F30: 1 unit model if implemented.
A31: Unique Unit | B31: Civ-specific unique unit(s) — general | C31: Every civ has 2+ unique units, either wholesale-new roles or stat/ability-modified replacements of a generic unit (e.g. Ghazi Raider replacing Horseman for Delhi Sultanate). | D31: Partial / Needs Audit | E31: Unique units do exist per civ — e.g. Maratha's Durg Garrison unit, and the 3 unique units already precedent for WeaponAttachment's hand-bone weapon system — but no session-log evidence gives a full per-civ roster count or confirms every civ has 2+, matching AoE IV's stated minimum. Recommend a dedicated audit pass (grep every civ's unit factories) before claiming parity either way. | F31: Depends on audit findings — likely 0-10 additional unit models depending on how many of the 5 civs fall short of a 2-unique-unit minimum. | G31: This row is explicitly flagged as needing verification, not assumed complete or incomplete.
A32: Unique Unit | B32: Unique-unit special abilities | C32: Replacement/variant unique units usually carry an active ability that further differentiates them from the generic unit they replace. | D32: Missing | E32: No active-ability system exists at all (see 'Ability' row in the main Comparison tab) — so even confirmed unique units in this project can only be stat-differentiated today, not ability-differentiated. | F32: Depends entirely on which abilities are designed per unique unit — icon + VFX + SFX per ability. | G32: Directly blocked on the Ability system gap in the main Comparison tab.
A33: Unique Unit | B33: Crusader Knight (base soldier body-swap) | C33: N/A — internal project item carried over for visibility, not an AoE roster entry. | D33: Blocked on asset re-sourcing | E33: 2 source glTF files were deleted as 'confirmed-unused asset scrap' and are unrecoverable from git history; blocked until replacement models are sourced. | F33: 2 new humanoid biped models — full spec already written in the project's own roadmap. | G33: Duplicated from the main Comparison tab for visibility alongside the rest of the unit roster.
A34: Unit Attribute | B34: Cost (multi-resource, typically 2-3 of Food/Wood/Gold) | C34: Nearly every unit costs a combination of resources, not just one. | D34: Implemented (assumed — verify) | E34: ResourceStockpile/CSV-driven unit data implies per-unit multi-resource costs (matching the 4-resource Wood/Food/Gold/Stone model), but no session-log entry explicitly confirms every unit costs 2-3 resources rather than 1 — recommend a quick data audit. | F34: None — data/code only.
A35: Unit Attribute | B35: Training time | C35: Time to produce a unit at its building, roughly proportional to cost. | D35: Implemented | E35: Barracks.RequestTrain and equivalent factory methods exist across all unit-producing buildings. | F35: None.
A36: Unit Attribute | B36: Line of Sight (per-unit vision radius) | C36: Each unit has its own sight range revealing fog of war. | D36: Missing | E36: No fog-of-war/vision-radius system exists at all (see the main Comparison tab's Fog of War row) — LOS as a per-unit stat is meaningless until that system exists. | F36: None — pure code, blocked on Fog of War being built first.
A37: Unit Attribute | B37: Hit points | C37: Core HP stat. | D37: Implemented | E37: Attackable.TakeDamage underlies all combat. | F37: None.
A38: Unit Attribute | B38: Speed | C38: Per-unit movement speed, upgradeable. | D38: Implemented | E38: Confirmed via team-bonus data (e.g. Maratha's +10% Cavalry move speed). | F38: None.
A39: Unit Attribute | B39: Armor | C39: Damage reduction stat(s), upgradeable via technology. | D39: Implemented (simplified — no melee/pierce split) | E39: ClassArmorBonus per UnitClass exists and is upgradeable (UpgradeProgress); confirmed live via Wall HP tests (250 -> 287.5 under an ally's team bonus). No evidence of AoE II's separate melee-armor vs. pierce-armor split. | F39: None — a formula-design question, not an asset gap.
A40: Unit Attribute | B40: Attacks (range, damage, Area of Effect defined per-attack, not per-unit) | C40: AoE IV defines each attack as its own object with its own range/damage/AoE, separate from the unit itself — letting one unit have multiple distinct attacks. | D40: Unclear / Needs Verification | E40: MeleeAttacker/BoatAttacker/BuildingAttacker exist as distinct attacker components with their own range/interval/splash, which is directionally similar, but it's unconfirmed whether a single unit can carry multiple simultaneous distinct attacks (AoE IV's actual model) versus one attack per unit (this project's apparent model). | F40: None — architecture question, not an asset gap.
A41: Unit Attribute | B41: Abilities (active, unit-triggered) | C41: Special active abilities separate from basic attack/move. | D41: Missing | E41: No active-ability system found anywhere (see main Comparison tab). | F41: Fully dependent on which abilities get designed.
A42: Unit Attribute | B42: Auras / enhancements | C42: Passive proximity-based buffs from a unit/building to nearby friendlies. | D42: Missing | E42: No spatial aura system; existing Team Bonuses are alliance-wide flat modifiers, not proximity-based (see main Comparison tab). | F42: 1 reusable aura-ring VFX + buff icon, per the main Comparison tab.
A43: Unit Attribute | B43: Batch/parallel training civ bonus (e.g. Mongols train 2-at-a-time for extra Stone) | C43: Some civs can bend the 'one unit at a time' training rule via a unique resource/mechanic. | D43: Missing | E43: Not found; no civ bonus in the session log resembles a training-throughput mechanic (existing civ bonuses are all passive stat/economy modifiers, not production-rate changes). | F43: None — pure code/data, a new CivilizationBonus entry. | G43: Would need its own explicit civ-bonus design, same convention as the 5 existing Team Bonuses.
A44: Unit Attribute | B44: Unit icon / portrait art | C44: Each unit has a UI icon shown in the build/train queue and selection panel. | D44: Unclear / Needs Verification | E44: BuildMenu's command-card icon pass covered ~24 buttons including buildings; whether every individual unit type (incl. civ-specific unique units) has its own distinct icon, versus a shared placeholder, is not explicitly confirmed in the session log. | F44: Icons for any unit type found to be missing one — small 2D icon per unit per civ where art differs.
A47: Summary — Unit Roster Status
A48: Status | B48: Count
A49: Partial — functional systems complete, visuals not sourced | B49: =COUNTIF(Units!D:D,A49)
A50: Missing | B50: =COUNTIF(Units!D:D,A50)
A51: Implemented | B51: =COUNTIF(Units!D:D,A51)
A52: Implemented (as generic 'Soldier') | B52: =COUNTIF(Units!D:D,A52)
A53: Missing — design question | B53: =COUNTIF(Units!D:D,A53)
A54: Implemented (as generic 'Cavalry') | B54: =COUNTIF(Units!D:D,A54)
A55: Partial | B55: =COUNTIF(Units!D:D,A55)
A56: Implemented (as the project's one generic 'Siege' unit) | B56: =COUNTIF(Units!D:D,A56)
A57: Missing — same design question as Handcannoneer | B57: =COUNTIF(Units!D:D,A57)
A58: Implemented (as the project's one generic 'War Galley') | B58: =COUNTIF(Units!D:D,A58)
A59: Partial / Needs Audit | B59: =COUNTIF(Units!D:D,A59)
A60: Blocked on asset re-sourcing | B60: =COUNTIF(Units!D:D,A60)
... A63: Unclear / Needs Verification | B63: =COUNTIF(Units!D:D,A63)
A64: Total unit/attribute rows assessed | B64: =SUM(B49:B63)
